pyalapin/__init__.py
pyalapin/engine/__init__.py
pyalapin/engine/color.py
pyalapin/engine/engine.py
pyalapin/engine/material.py
pyalapin/engine/move.py
pyalapin/interface/__init__.py
pyalapin/interface/color_edition.py
pyalapin/interface/colorize.py
pyalapin/interface/interface.py
pyalapin/player/__init__.py
pyalapin/player/ai_player.py
pyalapin/player/my_player.py
pyalapin/player/player.py
pyalapin/player/stockfish_player.py
pyalapin-1.0.0.dist-info/LICENSE.md
pyalapin-1.0.0.dist-info/METADATA
pyalapin-1.0.0.dist-info/WHEEL
pyalapin-1.0.0.dist-info/top_level.txt
pyalapin-1.0.0.dist-info/RECORD
