Metadata-Version: 2.1
Name: pyalapin
Version: 1.0.0
Summary: Custom chess engine built specifically to develop AIs
Author-email: Vincent Auriau <vincent.auriau.dev@gmail.com>
Project-URL: Homepage, https://github.com/VincentAuriau/custom-chess-engine
Project-URL: homepage, https://github.com/VincentAuriau/custom-chess-engine
Keywords: chess,ai,interface
Classifier: License :: OSI Approved :: MIT License
Classifier: Programming Language :: Python
Classifier: Programming Language :: Python :: 3
Classifier: Topic :: Games/Entertainment :: Board Games
Classifier: Topic :: Scientific/Engineering :: Artificial Intelligence
Requires-Python: >=3.8
License-File: LICENSE.md
Requires-Dist: numpy
Provides-Extra: dev
Requires-Dist: black ; extra == 'dev'
Requires-Dist: bumpver ; extra == 'dev'
Requires-Dist: isort ; extra == 'dev'
Requires-Dist: pip-tools ; extra == 'dev'
Requires-Dist: pytest ; extra == 'dev'
Requires-Dist: kivy ; extra == 'dev'
Requires-Dist: stockfish ; extra == 'dev'
